bytedbyteseer_chatllm_plugin_sdk/__init__.py
bytedbyteseer_chatllm_plugin_sdk-0.0.1.dist-info/METADATA
bytedbyteseer_chatllm_plugin_sdk-0.0.1.dist-info/WHEEL
bytedbyteseer_chatllm_plugin_sdk-0.0.1.dist-info/top_level.txt
bytedbyteseer_chatllm_plugin_sdk-0.0.1.dist-info/RECORD
