Metadata-Version: 2.1
Name: bytedbyteseer-chatllm-plugin-sdk
Version: 0.0.1
Summary: A simple package named bytedbyteseer_chatllm_plugin_sdk
Home-page: https://github.com/artifact/bytedbyteseer_chatllm_plugin_sdk.git
Author: artifact
Author-email: artifact@example.com
License: UNKNOWN
Platform: UNKNOWN
Classifier: Programming Language :: Python :: 3
Classifier: License :: OSI Approved :: MIT License
Classifier: Operating System :: OS Independent
